setup.py
bin/pgconn
pgconn/__init__.py
pgconn/argument_parser.py
pgconn/item_executor.py
pgconn/logger_factory.py
pgconn/menu_builder.py
pgconn/pg_info.py
pgconn/pg_pass_parser.py
pgconn.egg-info/PKG-INFO
pgconn.egg-info/SOURCES.txt
pgconn.egg-info/dependency_links.txt
pgconn.egg-info/not-zip-safe
pgconn.egg-info/requires.txt
pgconn.egg-info/top_level.txt