Metadata-Version: 1.0
Name: pgconn
Version: 0.2
Summary: Utility to connect to your Postgres DB using your .pgpass file
Home-page: http://github.com/dhydrated/pgconn
Author: Taufek Johar
Author-email: dhydrated@gmail.com
License: MIT
Platform: UNKNOWN
